irgen/__init__.py
irgen/__main__.py
irgen/raw.py
irgen-0.2.0.dist-info/LICENSE.txt
irgen-0.2.0.dist-info/METADATA
irgen-0.2.0.dist-info/WHEEL
irgen-0.2.0.dist-info/entry_points.txt
irgen-0.2.0.dist-info/top_level.txt
irgen-0.2.0.dist-info/RECORD
