Metadata-Version: 2.1
Name: irgen
Version: 0.2.0
Summary: A python tool for generating and converting ir formats
Home-page: https://github.com/elupus/irgen
Author: Joakim Plate
License: MIT
Platform: UNKNOWN
Classifier: License :: OSI Approved :: MIT License
Classifier: Development Status :: 4 - Beta
Classifier: Environment :: Console
Classifier: Environment :: Plugins
Requires-Python: >3.6
License-File: LICENSE.txt
Requires-Dist: asyncio
Requires-Dist: requests
Provides-Extra: tests
Requires-Dist: pytest (>3.6.4) ; extra == 'tests'
Requires-Dist: pytest-cov (<2.6) ; extra == 'tests'
Requires-Dist: coveralls ; extra == 'tests'
